manim_fonts/__init__.py
manim_fonts/_logging.py
manim_fonts/config.py
manim_fonts/download.py
manim_fonts/register_font.py
manim_fonts/utils.py
manim_fonts-0.5.0.dist-info/LICENSE
manim_fonts-0.5.0.dist-info/METADATA
manim_fonts-0.5.0.dist-info/WHEEL
manim_fonts-0.5.0.dist-info/entry_points.txt
manim_fonts-0.5.0.dist-info/RECORD
