Metadata-Version: 2.3
Name: manim-fonts
Version: 0.5.0
Summary: Use Fonts from Internet With Manim.
License: BSD-3-Clause
Author: Naveen M K
Author-email: naveen521kk@gmail.com
Requires-Python: >=3.9
Classifier: License :: OSI Approved :: BSD License
Classifier: Programming Language :: Python :: 3
Classifier: Programming Language :: Python :: 3.9
Classifier: Programming Language :: Python :: 3.10
Classifier: Programming Language :: Python :: 3.11
Classifier: Programming Language :: Python :: 3.12
Classifier: Programming Language :: Python :: 3.13
Requires-Dist: manim (>=0.3.0)
Requires-Dist: platformdirs (>=4)
Requires-Dist: requests (>=2.0.0)
Project-URL: Repository, https://github.com/naveen521kk/manim-fonts
